saq/__init__.py
saq/__main__.py
saq/errors.py
saq/job.py
saq/multiplexer.py
saq/py.typed
saq/runner.py
saq/types.py
saq/utils.py
saq/worker.py
saq/queue/__init__.py
saq/queue/base.py
saq/queue/http.py
saq/queue/postgres.py
saq/queue/postgres_migrations.py
saq/queue/redis.py
saq/web/__init__.py
saq/web/aiohttp.py
saq/web/common.py
saq/web/starlette.py
saq/web/static/app.js
saq/web/static/pico.min.css.gz
saq/web/static/snabbdom.js.gz
saq-0.26.1.dist-info/licenses/LICENSE
saq-0.26.1.dist-info/METADATA
saq-0.26.1.dist-info/WHEEL
saq-0.26.1.dist-info/entry_points.txt
saq-0.26.1.dist-info/top_level.txt
saq-0.26.1.dist-info/RECORD
