Metadata-Version: 2.4
Name: saq
Version: 0.26.1
Summary: Distributed Python job queue with asyncio and redis
Home-page: https://github.com/tobymao/saq
Author: Toby Mao
Author-email: toby.mao@gmail.com
License: MIT
Classifier: Development Status :: 5 - Production/Stable
Classifier: Framework :: AsyncIO
Classifier: Intended Audience :: Developers
Classifier: Intended Audience :: Information Technology
Classifier: Intended Audience :: System Administrators
Classifier: License :: OSI Approved :: MIT License
Classifier: Operating System :: MacOS
Classifier: Operating System :: POSIX :: Linux
Classifier: Operating System :: OS Independent
Classifier: Operating System :: Unix
Classifier: Programming Language :: Python
Classifier: Programming Language :: Python :: 3
Classifier: Programming Language :: Python :: 3 :: Only
Classifier: Programming Language :: Python :: 3.9
Classifier: Programming Language :: Python :: 3.10
Classifier: Programming Language :: Python :: 3.11
Classifier: Programming Language :: Python :: 3.12
Classifier: Programming Language :: Python :: 3.13
Classifier: Topic :: Internet
Classifier: Topic :: Software Development :: Libraries :: Python Modules
Classifier: Topic :: System :: Distributed Computing
Classifier: Topic :: System :: Monitoring
Classifier: Topic :: System :: Systems Administration
License-File: LICENSE
Requires-Dist: croniter>=0.3.18
Provides-Extra: hiredis
Requires-Dist: redis[hiredis]>=4.2.0; extra == "hiredis"
Provides-Extra: http
Requires-Dist: aiohttp; extra == "http"
Provides-Extra: postgres
Requires-Dist: psycopg[pool]>=3.2.0; extra == "postgres"
Provides-Extra: redis
Requires-Dist: redis<7.0,>=4.2; extra == "redis"
Provides-Extra: web
Requires-Dist: aiohttp; extra == "web"
Requires-Dist: aiohttp_basicauth; extra == "web"
Provides-Extra: dev
Requires-Dist: aiohttp; extra == "dev"
Requires-Dist: aiohttp_basicauth; extra == "dev"
Requires-Dist: coverage; extra == "dev"
Requires-Dist: mypy; extra == "dev"
Requires-Dist: psycopg[pool]>=3.2.0; extra == "dev"
Requires-Dist: pre-commit; extra == "dev"
Requires-Dist: redis<7.0,>=4.2; extra == "dev"
Requires-Dist: ruff; extra == "dev"
Requires-Dist: time-machine; extra == "dev"
Requires-Dist: types-croniter; extra == "dev"
Requires-Dist: types-redis; extra == "dev"
Requires-Dist: types-setuptools; extra == "dev"
Requires-Dist: starlette; extra == "dev"
Requires-Dist: httpx; extra == "dev"
Dynamic: author
Dynamic: author-email
Dynamic: classifier
Dynamic: description
Dynamic: description-content-type
Dynamic: home-page
Dynamic: license
Dynamic: license-file
Dynamic: provides-extra
Dynamic: requires-dist
Dynamic: summary
